README.md
setup.py
qth_gc/__init__.py
qth_gc/version.py
qth_gc.egg-info/PKG-INFO
qth_gc.egg-info/SOURCES.txt
qth_gc.egg-info/dependency_links.txt
qth_gc.egg-info/entry_points.txt
qth_gc.egg-info/requires.txt
qth_gc.egg-info/top_level.txt