Metadata-Version: 2.1
Name: qth-gc
Version: 0.2.0
Summary: Deletes Qth properties and other retained MQTT messages with which no client is affiliated.
Home-page: https://github.com/mossblaser/qth_gc
Author: Jonathan Heathcote
License: GPLv2
Keywords: mqtt asyncio home-automation messaging
Platform: UNKNOWN
Classifier: Development Status :: 3 - Alpha
Classifier: Intended Audience :: Developers
Classifier: License :: OSI Approved :: GNU General Public License v2 (GPLv2)
Classifier: Operating System :: POSIX :: Linux
Classifier: Operating System :: Microsoft :: Windows
Classifier: Operating System :: MacOS
Classifier: Programming Language :: Python :: 3
Classifier: Programming Language :: Python :: 3.10
